tuxtoaster/__init__.py
tuxtoaster/__main__.py
tuxtoaster/main.py
tuxtoaster/multi_runner.py
tuxtoaster/assets/__init__.py
tuxtoaster/assets/banner.py
tuxtoaster/assets/descriptions.py
tuxtoaster/assets/submenus.py
tuxtoaster/cpu/__init__.py
tuxtoaster/cpu/all_cores.py
tuxtoaster/cpu/custom_cpu.py
tuxtoaster/cpu/single_core.py
tuxtoaster/disk/__init__.py
tuxtoaster/disk/disk_buffcachewrites.py
tuxtoaster/disk/disk_bwrandomrw.py
tuxtoaster/disk/disk_bwreads.py
tuxtoaster/disk/disk_bwrw.py
tuxtoaster/disk/disk_bwwrites.py
tuxtoaster/disk/disk_cachewriteswarmup.py
tuxtoaster/disk/disk_iorandomrw.py
tuxtoaster/disk/disk_ioreads.py
tuxtoaster/disk/disk_iorw.py
tuxtoaster/disk/disk_iowrites.py
tuxtoaster/disk/disk_utils.py
tuxtoaster/memory/__init__.py
tuxtoaster/memory/mem_multithread.py
tuxtoaster/memory/mem_singlethread.py
tuxtoaster/memory/mem_spikes.py
tuxtoaster/memory/mem_uncleangc.py
tuxtoaster/network/__init__.py
tuxtoaster/network/network_in.py
tuxtoaster/network/network_in_multi.py
tuxtoaster/network/network_out.py
tuxtoaster/network/network_out_multi.py
tuxtoaster/network/network_simulate_latency.py
tuxtoaster/network/network_socket_exhaustion.py
tuxtoaster-1.2.10.dist-info/LICENSE
tuxtoaster-1.2.10.dist-info/METADATA
tuxtoaster-1.2.10.dist-info/WHEEL
tuxtoaster-1.2.10.dist-info/entry_points.txt
tuxtoaster-1.2.10.dist-info/top_level.txt
tuxtoaster-1.2.10.dist-info/RECORD
