Metadata-Version: 2.1
Name: tuxtoaster
Version: 1.2.10
Summary: All-in-one Linux stress and benchmarking toolkit
Home-page: UNKNOWN
License: UNKNOWN
Platform: UNKNOWN
Requires-Python: >=3.6
License-File: LICENSE
Requires-Dist: psutil (>=5.9)
Requires-Dist: simple-term-menu (>=1.6.1)
Requires-Dist: importlib-metadata (<5,>=4) ; python_version < "3.8"
